azure_jobs/__init__.py
azure_jobs/cli.py
azure_jobs/conf.py
azure_jobs/const.py
azure_jobs/template.py
azure_jobs/toml.py
azure_jobs-0.1.12.dist-info/METADATA
azure_jobs-0.1.12.dist-info/WHEEL
azure_jobs-0.1.12.dist-info/entry_points.txt
azure_jobs-0.1.12.dist-info/RECORD
