Metadata-Version: 2.4
Name: azure_jobs
Version: 0.1.12
Summary: Add your description here
Author-email: HSPK <whxway@whu.edu.cn>
Requires-Python: >=3.10
Requires-Dist: click>=8.2.1
Requires-Dist: pyyaml>=6.0.2
